seeuletter/__init__.py
seeuletter/api_requestor.py
seeuletter/compat.py
seeuletter/error.py
seeuletter/resource.py
seeuletter/version.py
seeuletter-1.2.0.dist-info/LICENSE
seeuletter-1.2.0.dist-info/METADATA
seeuletter-1.2.0.dist-info/WHEEL
seeuletter-1.2.0.dist-info/top_level.txt
seeuletter-1.2.0.dist-info/RECORD
